[
    {
        "dasar": "ka",
        "abjad": "k",
        "arti": [
            {
                "definisi_umum": [
                    {
                        "definisi": "kak; singkatan dari kakak",
                        "kelaskata": "n",
                        "contoh": [
                            {
                                "banjar": "ka mana ka?",
                                "indonesia": "ke mana kak?"
                            }
                        ]
                    }
                ]
            }
        ]
    }
]